awsgitops/__init__.py
awsgitops/__main__.py
awsgitops/awsgitops.py
awsgitops/generators/__init__.py
awsgitops/generators/dummy.py
awsgitops/generators/dummytwo.py
awsgitops/generators/eks.py
awsgitops/generators/genlauncher.py
awsgitops/generators/rds.py
awsgitops/generators/spec.py
awsgitops/modules/__init__.py
awsgitops/modules/file_ops.py
awsgitops/modules/util.py
aws_gitops-1.3.0.dist-info/LICENSE
aws_gitops-1.3.0.dist-info/METADATA
aws_gitops-1.3.0.dist-info/WHEEL
aws_gitops-1.3.0.dist-info/entry_points.txt
aws_gitops-1.3.0.dist-info/top_level.txt
aws_gitops-1.3.0.dist-info/RECORD
